watlab/__init__.py
watlab/hydroflow.py
watlab/meshParser.py
watlab/sediflow.py
watlab/utils.py
watlab/watlab.py
watlab/bin/hydroflow-darwin
watlab/bin/hydroflow-linux
watlab/bin/hydroflow-parallel-darwin
watlab/bin/hydroflow-parallel-linux
watlab/bin/hydroflow-parallel-win.exe
watlab/bin/hydroflow-win.exe
watlab/bin/libgcc_s_seh-1.dll
watlab/bin/libgomp-1.dll
watlab/bin/libstdc++-6.dll
watlab/bin/libwinpthread-1.dll
watlab/bin/meshchecker-darwin
watlab/bin/meshchecker-linux
watlab/bin/meshchecker-win.exe
watlab/data/data_template.txt
watlab-0.5.1.dist-info/licenses/AUTHORS.txt
watlab-0.5.1.dist-info/licenses/COPYING
watlab-0.5.1.dist-info/licenses/LICENSE
watlab-0.5.1.dist-info/METADATA
watlab-0.5.1.dist-info/WHEEL
watlab-0.5.1.dist-info/top_level.txt
watlab-0.5.1.dist-info/RECORD
