Metadata-Version: 2.4
Name: watlab
Version: 0.5.1
Summary: The watlab package is a Python interface for the C++-based hydraulical simulation sandbox. It is intended mainly for scholars.
Author-email: Sandra Soares-Frazão <sandra.soares-frazao@uclouvain.be>
Maintainer-email: Pierre-Yves Gousenbourger <pierre-yves.gousenbourger@uclouvain.be>, Nathan Delpierre <nathan.delpierre@uclouvain.be>, Martin Petitjean <martin.petitjean@uclouvain.be>
License: GNU General Public License v3 or later (GPLv3+)
Project-URL: Homepage, https://sites.uclouvain.be/hydraulics-group/watlab/
Project-URL: Bug Tracker, https://forge.uclouvain.be/hydraulics-simulations/hydroflow/-/issues
Classifier: Programming Language :: Python :: 3
Classifier: Programming Language :: C++
Classifier: License :: OSI Approved :: GNU General Public License v3 or later (GPLv3+)
Classifier: Operating System :: OS Independent
Classifier: Development Status :: 2 - Pre-Alpha
Classifier: Environment :: Console
Classifier: Intended Audience :: Education
Classifier: Intended Audience :: Science/Research
Classifier: Natural Language :: English
Requires-Python: >=3.10
License-File: LICENSE
License-File: COPYING
License-File: AUTHORS.txt
Requires-Dist: gmsh==4.11
Requires-Dist: numpy<2.0.0,>=1.26
Requires-Dist: matplotlib>=3.8
Requires-Dist: rasterio>=1.3
Requires-Dist: scipy>=1.11
Requires-Dist: pandas>=2.1
Requires-Dist: contextily>=1.4.0
Requires-Dist: imageio>=2.32
Requires-Dist: imageio-ffmpeg>=0.4
Requires-Dist: openpyxl>=3.1.5
Requires-Dist: netCDF4>=1.7
Dynamic: license-file
